aioredlock_py/__init__.py
aioredlock_py/redisson.py
aioredlock_py-0.1.5.dist-info/LICENSE
aioredlock_py-0.1.5.dist-info/METADATA
aioredlock_py-0.1.5.dist-info/WHEEL
aioredlock_py-0.1.5.dist-info/top_level.txt
aioredlock_py-0.1.5.dist-info/RECORD
