Metadata-Version: 2.1
Name: aioredlock-py
Version: 0.1.5
Summary: Secure and efficient distributed locks (Radisson like) implemetation
Home-page: https://github.com/GoodManWEN/aioredlock_py
Author: WEN
License: UNKNOWN
Keywords: aioredlock_py,redlock,redisson,redis,aioredis,aioredlock,redis-py
Platform: UNKNOWN
Classifier: Programming Language :: Python :: 3
Classifier: Programming Language :: Python :: 3.7
Classifier: Programming Language :: Python :: 3.8
Classifier: Programming Language :: Python :: 3.9
Classifier: Programming Language :: Python :: 3.10
Classifier: License :: OSI Approved :: MIT License
Classifier: Operating System :: POSIX :: Linux
Classifier: Operating System :: Microsoft :: Windows
Classifier: Framework :: AsyncIO
Requires-Python: >=3.7
Requires-Dist: aioredis (>=2.0.0)
